huggingface_text_data_analyzer/__init__.py
huggingface_text_data_analyzer/cli.py
huggingface_text_data_analyzer/main.py
huggingface_text_data_analyzer/src/advanced_analyzer.py
huggingface_text_data_analyzer/src/base_analyzer.py
huggingface_text_data_analyzer/src/report_generator.py
huggingface_text_data_analyzer/src/utils.py
huggingface_text_data_analyzer/src/viz_generator.py
huggingface_text_data_analyzer-1.1.0.dist-info/LICENSE
huggingface_text_data_analyzer-1.1.0.dist-info/METADATA
huggingface_text_data_analyzer-1.1.0.dist-info/WHEEL
huggingface_text_data_analyzer-1.1.0.dist-info/entry_points.txt
huggingface_text_data_analyzer-1.1.0.dist-info/top_level.txt
huggingface_text_data_analyzer-1.1.0.dist-info/RECORD
