Metadata-Version: 2.1
Name: huggingface-text-data-analyzer
Version: 1.1.0
Summary: A comprehensive tool for analyzing text datasets from HuggingFace's datasets library
Home-page: https://github.com/SulRash/huggingface-text-data-analyzer
Author: Sultan Alrashed
Author-email: sultan.m.rashed@gmail.com
Project-URL: Bug Tracker, https://github.com/SulRash/huggingface-text-data-analyzer/issues
Project-URL: Documentation, https://github.com/SulRash/huggingface-text-data-analyzer#readme
Project-URL: Source Code, https://github.com/SulRash/huggingface-text-data-analyzer
Keywords: nlp,text-analysis,huggingface,datasets,machine-learning,data-analysis,text-processing
Classifier: Development Status :: 3 - Alpha
Classifier: Intended Audience :: Science/Research
Classifier: Intended Audience :: Developers
Classifier: License :: OSI Approved :: Apache Software License
Classifier: Programming Language :: Python :: 3
Classifier: Programming Language :: Python :: 3.8
Classifier: Programming Language :: Python :: 3.9
Classifier: Programming Language :: Python :: 3.10
Classifier: Programming Language :: Python :: 3.11
Classifier: Topic :: Scientific/Engineering :: Artificial Intelligence
Classifier: Topic :: Text Processing :: General
Classifier: Operating System :: OS Independent
Requires-Python: >=3.8
License-File: LICENSE
Requires-Dist: transformers>=4.0.0
Requires-Dist: datasets>=2.0.0
Requires-Dist: torch>=1.0.0
Requires-Dist: rich>=10.0.0
Requires-Dist: spacy>=3.0.0
Requires-Dist: pandas>=1.0.0
Requires-Dist: numpy>=1.19.0
Requires-Dist: scikit-learn>=0.24.0
Requires-Dist: tqdm>=4.0.0
